my_matlab_server/__init__.py
my_matlab_server/server.py
matlab_mcp-0.1.4.dist-info/METADATA
matlab_mcp-0.1.4.dist-info/WHEEL
matlab_mcp-0.1.4.dist-info/entry_points.txt
matlab_mcp-0.1.4.dist-info/licenses/LICENSE
matlab_mcp-0.1.4.dist-info/RECORD
