Metadata-Version: 2.4
Name: matlab-mcp
Version: 0.1.4
Summary: MATLAB MCP Server - A Model Context Protocol server for MATLAB integration (requires Python 3.11+)
Author-email: liou <liou666@126.com>
License-Expression: MIT
License-File: LICENSE
Keywords: ai,assistant,matlab,mcp,model-context-protocol
Classifier: Development Status :: 3 - Alpha
Classifier: Intended Audience :: Developers
Classifier: License :: OSI Approved :: MIT License
Classifier: Programming Language :: Python :: 3
Classifier: Programming Language :: Python :: 3.11
Classifier: Programming Language :: Python :: 3.12
Classifier: Topic :: Scientific/Engineering
Classifier: Topic :: Software Development :: Libraries :: Python Modules
Requires-Python: <3.12,>=3.11
Requires-Dist: mcp[cli]
Requires-Dist: setuptools
